Metadata-Version: 1.0
Name: fakearray
Version: 1.0.2
Summary: simulated n-dimensional array data
Home-page: https://github.com/jasminetstone/fakearray
Author: jasminetstone
Author-email: jasminetstone@gmail.com
License: MIT
Platform: UNKNOWN
